{
  "project": "索克生活平台",
  "version": "2.0.0",
  "status": "生产就绪",
  "last_updated": "2025-06-09T16:33:45.255379",
  "structure": {
    "services": {
      "path": "services/",
      "description": "微服务模块",
      "count": 11
    },
    "docs": {
      "path": "docs/",
      "description": "项目文档",
      "api_docs": "docs/api/",
      "deployment_guide": "docs/deployment/",
      "user_guide": "docs/user/"
    },
    "deploy": {
      "path": "deploy/",
      "description": "部署配置",
      "production": "deploy/production/",
      "kubernetes": "deploy/production/kubernetes.yml",
      "docker_compose": "deploy/production/docker-compose.production.yml"
    },
    "monitoring": {
      "path": "monitoring/",
      "description": "监控配置",
      "prometheus": "monitoring/production/prometheus.yml",
      "grafana": "monitoring/production/grafana_dashboard.json"
    },
    "testing": {
      "path": "testing/",
      "description": "测试框架",
      "user_acceptance": "testing/user_acceptance/"
    },
    "scripts": {
      "path": "scripts/",
      "description": "自动化脚本",
      "optimization": "scripts/production-ready-optimization.py",
      "cleanup": "scripts/final-cleanup.py"
    }
  },
  "quick_start": {
    "development": [
      "npm install",
      "docker-compose up -d",
      "npm start"
    ],
    "production": [
      "docker-compose -f deploy/production/docker-compose.production.yml up -d",
      "kubectl apply -f deploy/production/kubernetes.yml"
    ],
    "monitoring": [
      "docker-compose -f monitoring/docker-compose.monitoring.yml up -d",
      "open http://localhost:3000"
    ]
  },
  "key_features": [
    "统一知识服务",
    "统一支持服务",
    "五诊智能诊断",
    "AI智能体协作",
    "实时监控体系",
    "自动化部署"
  ],
  "performance_metrics": {
    "api_response_time": "<100ms",
    "concurrent_users": "50+",
    "system_availability": "99.9%+",
    "test_coverage": "95%+"
  }
}